[
{
  "apptype": "1",
  "code": "81H10535",
  "creationtime": "2021-08-09 15:09:49",
  "creator": "~",
  "dr": "0",
  "fun_property": "0",
  "funtype": "0",
  "height": "1",
  "image_src": "businessprocess",
  "iscauserusable": "N",
  "iscopypage": "N",
  "isenable": "Y",
  "mdid": "ccc5f89d-422c-4252-9bee-1df51539cf30",
  "modifier": "~",
  "resid": "",
  "name": "客情接待申请单",
  "orgtypecode": "GLOBLE00000000000000",
  "own_module": "81H1",
  "parent_id": "81H105",
  "pk_appregister": "PK_APP",
  "pk_group": "~",
  "source_app_code": "81H10535",
  "ts": "2021-08-09 15:09:49",
  "uselicense_load": "Y",
  "width": "1"
},
{
"apptype": "1",
"code": "81H10535A",
"creationtime": "2021-08-09 15:09:49",
"creator": "~",
"dr": "0",
"fun_property": "0",
"funtype": "0",
"height": "1",
"image_src": "businessprocess",
"iscauserusable": "N",
"iscopypage": "N",
"isenable": "Y",
"mdid": "ccc5f89d-422c-4252-9bee-1df51539cf30",
"modifier": "~",
"resid": "",
"name": "客情接待申请单审批",
"orgtypecode": "GLOBLE00000000000000",
"own_module": "81H1",
"parent_id": "81H105",
"pk_appregister": "PK_APP1",
"pk_group": "~",
"source_app_code": "81H10535A",
"ts": "2021-08-09 15:09:49",
"uselicense_load": "Y",
"width": "1"
}
]